INDOML/__init__.py
INDOML/datamanipulasi/__init__.py
INDOML/datamanipulasi/fold.py
INDOML/graph/__init__.py
INDOML/graph/tree.py
INDOML/matematika/__init__.py
INDOML/matematika/distance.py
INDOML/matematika/error.py
INDOML/model/Ensemble.py
INDOML/model/__init__.py
INDOML/model/supervised.py
INDOML/model/unsupervised.py
INDOML/post_processing/__init__.py
INDOML/post_processing/evaluasi.py
INDOML/pre_proceesing/EDA.py
INDOML/pre_proceesing/__init__.py
INDOML/searching/__init__.py
INDOML/searching/evolutionary.py
INDOML/searching/test_evolutionary.py
INDOML/swarm/__init__.py
INDOML/swarm/evolutionary.py
INDOML-0.0.33.dist-info/LICENSE
INDOML-0.0.33.dist-info/METADATA
INDOML-0.0.33.dist-info/WHEEL
INDOML-0.0.33.dist-info/top_level.txt
INDOML-0.0.33.dist-info/RECORD
