Metadata-Version: 2.1
Name: INDOML
Version: 0.0.33
Summary: package machine learning buatan indonesia
Home-page: https://github.com/khalifardy/library_machine_learning
Author: Miko
Author-email: khalifardy.miqdarsah@gmail.com
License: GNU
Classifier: License :: OSI Approved :: GNU General Public License v3 (GPLv3)
Classifier: Operating System :: OS Independent
Classifier: Programming Language :: Python :: 3.10
Requires-Python: >=3.10
License-File: LICENSE
Requires-Dist: numpy >=1.26.2
Requires-Dist: seaborn >=0.13.0
Requires-Dist: matplotlib >=3.8.2
Requires-Dist: scikit-learn >=1.3.2
Requires-Dist: pandas >=2.1.4
